serde_mol2-0.2.4.data/scripts/serde-mol2
serde_mol2/serde_mol2.cpython-310-x86_64-linux-gnu.so
serde_mol2/__init__.py
serde_mol2-0.2.4.dist-info/WHEEL
serde_mol2-0.2.4.dist-info/METADATA
serde_mol2-0.1.2.dist-info/RECORD
