Metadata-Version: 2.1
Name: serde_mol2
Version: 0.2.4
Classifier: Programming Language :: Rust
Classifier: Operating System :: POSIX :: Linux
Author: Jaroslaw Kalinowski <jaroslaw.kalinowski@csc.fi>
Author-email: Jaroslaw Kalinowski <jaroslaw.kalinowski@csc.fi>
Requires-Python: >=3.8
